[
  {
    "outfit_name": "Logo Jacket",
    "price": 50.99,
    "brand": "Jaded London",
    "location": "Urban Outfiters",
    "occasion": "Casual",
    "colour": "Beige",
    "notes": "100% cotton",
    "image": "https://res.cloudinary.com/do5244w1d/image/upload/v1623273581/outfit1_c5pv5k.jpg",
    "gender": "Men",
    "user_id": 1
  },
  {
    "outfit_name": "Floral shirt",
    "price": 24.99,
    "brand": "Hermano",
    "location": "Asos",
    "occasion": "Casual",
    "colour": "Green",
    "notes": "Short sleeves",
    "image": "https://res.cloudinary.com/do5244w1d/image/upload/v1623273581/outfit2_cchdel.jpg",
    "gender": "Men",
    "user_id": 1
  },
  {
    "outfit_name": "Shirt",
    "price": 34.9,
    "brand": "Zara",
    "location": "Zara",
    "occasion": "Casual",
    "colour": "Navy",
    "notes": "Line fabric",
    "image": "https://res.cloudinary.com/do5244w1d/image/upload/v1623273581/outfit3_mu8ptq.jpg",
    "gender": "Men",
    "user_id": 1
  },
  {
    "outfit_name": "Floral print shirt",
    "price": 24.99,
    "brand": "Top Man",
    "location": "Top Man",
    "occasion": "Casual",
    "colour": "Green",
    "notes": "Short sleeves",
    "image": "https://res.cloudinary.com/do5244w1d/image/upload/v1623273582/outfit4_tdyuxm.jpg",
    "gender": "Men",
    "user_id": 1
  },
  {
    "outfit_name": "Varsity Jacket",
    "price": 50.99,
    "brand": "Jaded London",
    "location": "Urban Outfiters",
    "occasion": "Casual",
    "colour": "Blue",
    "notes": "Comfy",
    "image": "https://res.cloudinary.com/do5244w1d/image/upload/v1623273581/outfit5_llaspa.jpg",
    "gender": "Men",
    "user_id": 1
  },
  {
    "outfit_name": "T-shirt",
    "price": 24.99,
    "brand": "Pull&Bear",
    "location": "Pull&Bear",
    "occasion": "Casual",
    "colour": "White",
    "notes": "Relaxed design",
    "image": "https://res.cloudinary.com/do5244w1d/image/upload/v1623273581/outfit6_ubi5kh.jpg",
    "gender": "Men",
    "user_id": 1
  },
  {
    "outfit_name": "T-shirt",
    "price": 34.99,
    "brand": "Mango",
    "location": "Mango",
    "occasion": "Elegant",
    "colour": "Beige",
    "notes": "Slim fit",
    "image": "https://res.cloudinary.com/do5244w1d/image/upload/v1623273582/outfit7_xianuw.jpg",
    "gender": "Men",
    "user_id": 2
  },
  {
    "outfit_name": "Wide Trousers",
    "price": 40.0,
    "brand": "Mango",
    "location": "Mango",
    "occasion": "Casual",
    "colour": "Green",
    "notes": "Wide Leg",
    "image": "https://res.cloudinary.com/do5244w1d/image/upload/v1623273582/outfit8_n3puq9.jpg",
    "gender": "Women",
    "user_id": 2
  },
  {
    "outfit_name": "Long Jacket",
    "price": 70.99,
    "brand": "Ralph Lauren",
    "location": "Next",
    "occasion": "Casual",
    "colour": "Beige",
    "notes": "Waterproof",
    "image": "https://res.cloudinary.com/do5244w1d/image/upload/v1623273582/outfit9_dzxqtk.jpg",
    "gender": "Women",
    "user_id": 2
  },
  {
    "outfit_name": "Leather Trousers",
    "price": 50.6,
    "brand": "Monky",
    "location": "Monky",
    "occasion": "Night Out",
    "colour": "Black",
    "notes": "Slim fit",
    "image": "https://res.cloudinary.com/do5244w1d/image/upload/v1623273580/outfit10_l5s1wu.jpg",
    "gender": "Women",
    "user_id": 2
  },
  {
    "outfit_name": "Print Dress",
    "price": 40.0,
    "brand": "Zara",
    "location": "Zara",
    "occasion": "Night Out",
    "colour": "Green",
    "notes": "Lycra",
    "image": "https://res.cloudinary.com/do5244w1d/image/upload/v1623273580/outfit11_bx22wx.jpg",
    "gender": "Women",
    "user_id": 2
  },
  {
    "outfit_name": "Dress-Jacket",
    "price": 76.0,
    "brand": "Uniqlo",
    "location": "Uniqlo",
    "occasion": "Casual",
    "colour": "Purple",
    "notes": "Cotton",
    "image": "https://res.cloudinary.com/do5244w1d/image/upload/v1623273580/outfit12_dyrdtu.jpg",
    "gender": "Women",
    "user_id": 3
  },
  {
    "outfit_name": "Shorts",
    "price": 50.0,
    "brand": "Levi's",
    "location": "Urban Outfiters",
    "occasion": "Casual",
    "colour": "Blue",
    "notes": "Jeans",
    "image": "https://res.cloudinary.com/do5244w1d/image/upload/v1623273581/outfit13_abgx16.jpg",
    "gender": "Women",
    "user_id": 3
  },
  {
    "outfit_name": "Dress",
    "price": 65.0,
    "brand": "Tommy Hilfiger",
    "location": "Urban Outfiters",
    "occasion": "Casual",
    "colour": "White",
    "notes": "Animal print",
    "image": "https://res.cloudinary.com/do5244w1d/image/upload/v1623273580/outfit16_cigil1.jpg",
    "gender": "Women",
    "user_id": 3
  },
  {
    "outfit_name": "Print T-Shirt",
    "price": 35.0,
    "brand": "4500",
    "location": "Urban Outfiters",
    "occasion": "Casual",
    "colour": "White",
    "notes": "Lycra",
    "image": "https://res.cloudinary.com/do5244w1d/image/upload/v1623273580/outfit15_otcjzo.jpg",
    "gender": "Women",
    "user_id": 3
  },
  {
    "outfit_name": "Dress",
    "price": 75.0,
    "brand": "TT212",
    "location": "Urban Outfiters",
    "occasion": "Casual",
    "colour": "White",
    "notes": "Vest with frontal zip",
    "image": "https://res.cloudinary.com/do5244w1d/image/upload/v1623273580/outfit16_cigil1.jpg",
    "gender": "Women",
    "user_id": 3
  },
  {
    "outfit_name": "T-shirt",
    "price": 75.0,
    "brand": "Foo Fighters",
    "location": "Urban Outfiters",
    "occasion": "Night Out",
    "colour": "White",
    "notes": "Cool t-shirt with an snake print",
    "image": "https://res.cloudinary.com/dw8fpwkkn/image/upload/v1623430908/outfit43_d89iyd.jpg",
    "gender": "Men",
    "user_id": 3
  },
  {
    "outfit_name": "Jumper",
    "price": 82.0,
    "brand": "Foo Fighters",
    "location": "Urban Outfiters",
    "occasion": "Sportwear",
    "colour": "Orange",
    "notes": "Cool t-shirt with an snake print",
    "image": "https://res.cloudinary.com/dw8fpwkkn/image/upload/v1623430907/outfit44_dxb24k.jpg",
    "gender": "Unisex",
    "user_id": 3
  },
  {
    "outfit_name": "Trousers",
    "price": 35.0,
    "brand": "Tribute",
    "location": "Next",
    "occasion": "Wedding",
    "colour": "Green",
    "notes": "Cool t-shirt with an snake print",
    "image": "https://res.cloudinary.com/dw8fpwkkn/image/upload/v1623430907/outfit38_qybxb1.jpg",
    "gender": "Men",
    "user_id": 3
  },
  {
    "outfit_name": "Shorts",
    "price": 33.0,
    "brand": "River Island",
    "location": "River Island",
    "occasion": "Night Out",
    "colour": "Brown",
    "notes": "Comfy shorts",
    "image": "https://res.cloudinary.com/dw8fpwkkn/image/upload/v1623430907/outfit42_se4vku.jpg",
    "gender": "Men",
    "user_id": 3
  },
  {
    "outfit_name": "Total look",
    "price": 95.3,
    "brand": "River Island",
    "location": "River Island",
    "occasion": "Night Out",
    "colour": "White",
    "notes": "Comfy shorts",
    "image": "https://res.cloudinary.com/dw8fpwkkn/image/upload/v1623430907/outfit40_sqaisd.jpg",
    "gender": "Men",
    "user_id": 3
  },
  {
    "outfit_name": "Total ourtfit",
    "price": 95.3,
    "brand": "Zara",
    "location": "Zara",
    "occasion": "Workwear",
    "colour": "Multi",
    "notes": "All the outfit is from zara",
    "image": "https://res.cloudinary.com/dw8fpwkkn/image/upload/v1623430906/outfit41_htjxxn.jpg",
    "gender": "Men",
    "user_id": 3
  },
  {
    "outfit_name": "Total outfit",
    "price": 87.7,
    "brand": "River Island",
    "location": "River Island",
    "occasion": "Workwear",
    "colour": "Multi",
    "notes": "All from River Island",
    "image": "https://res.cloudinary.com/dw8fpwkkn/image/upload/v1623430906/outfit36_tgdwtn.jpg",
    "gender": "Men",
    "user_id": 3
  },
  {
    "outfit_name": "Casual outfit",
    "price": 87.7,
    "brand": "Carhartt",
    "location": "Carhartt",
    "occasion": "Workwear",
    "colour": "Multi",
    "notes": "All from River Island",
    "image": "https://res.cloudinary.com/dw8fpwkkn/image/upload/v1623430906/outfit39_x56nnr.jpg",
    "gender": "Men",
    "user_id": 3
  },
  {
    "outfit_name": "Pink Dress",
    "price": 37.7,
    "brand": "H&M",
    "location": "H&M",
    "occasion": "Night Out",
    "colour": "Pink",
    "notes": "Perfect",
    "image": "https://res.cloudinary.com/dw8fpwkkn/image/upload/v1623430906/outfit32_qh4tjs.jpg",
    "gender": "Women",
    "user_id": 3
  },
  {
    "outfit_name": "Perfect summer",
    "price": 97.7,
    "brand": "H&M",
    "location": "H&M",
    "occasion": "Workwear",
    "colour": "Multi",
    "notes": "Perfect",
    "image": "https://res.cloudinary.com/dw8fpwkkn/image/upload/v1623430905/outfit37_ijsm82.jpg",
    "gender": "Men",
    "user_id": 3
  },
  {
    "outfit_name": "Summer vibes",
    "price": 57.7,
    "brand": "H&M",
    "location": "H&M",
    "occasion": "Workwear",
    "colour": "Black",
    "notes": "Perfect",
    "image": "https://res.cloudinary.com/dw8fpwkkn/image/upload/v1623430904/outfit35_bxitrq.jpg",
    "gender": "Men",
    "user_id": 3
  },
  {
    "outfit_name": "Summer sunset",
    "price": 77.7,
    "brand": "H&M",
    "location": "H&M",
    "occasion": "Night Out",
    "colour": "Multi",
    "notes": "Perfect",
    "image": "https://res.cloudinary.com/dw8fpwkkn/image/upload/v1623430904/outfit29_gylwpj.jpg",
    "gender": "Women",
    "user_id": 3
  },
  {
    "outfit_name": "Picnic",
    "price": 37.7,
    "brand": "H&M",
    "location": "H&M",
    "occasion": "Other",
    "colour": "Blue",
    "notes": "Good quality",
    "image": "https://res.cloudinary.com/dw8fpwkkn/image/upload/v1623430904/outfit30_tnmdxq.jpg",
    "gender": "Women",
    "user_id": 3
  },
  {
    "outfit_name": "Perfect look",
    "price": 97.7,
    "brand": "H&M",
    "location": "H&M",
    "occasion": "Wedding",
    "colour": "Multi",
    "notes": "Good quality",
    "image": "https://res.cloudinary.com/dw8fpwkkn/image/upload/v1623430904/outfit33_gbqe6o.jpg",
    "gender": "Women",
    "user_id": 3
  },
  {
    "outfit_name": "Perfect look",
    "price": 67.7,
    "brand": "H&M",
    "location": "H&M",
    "occasion": "Other",
    "colour": "Multi",
    "notes": "Good quality",
    "image": "https://res.cloudinary.com/dw8fpwkkn/image/upload/v1623430904/outfit34_wm1hcp.jpg",
    "gender": "Women",
    "user_id": 3
  },
  {
    "outfit_name": "Perfect vest",
    "price": 57.7,
    "brand": "H&M",
    "location": "H&M",
    "occasion": "Wedding",
    "colour": "Black",
    "notes": "Good quality",
    "image": "https://res.cloudinary.com/dw8fpwkkn/image/upload/v1623430903/outfit31_e2iwdq.jpg",
    "gender": "Women",
    "user_id": 3
  },
  {
    "outfit_name": "Total look",
    "price": 57.7,
    "brand": "H&M",
    "location": "H&M",
    "occasion": "Other",
    "colour": "Multi",
    "notes": "Good quality",
    "image": "https://res.cloudinary.com/dw8fpwkkn/image/upload/v1623430901/outfit25_tiyhbo.jpg",
    "gender": "Women",
    "user_id": 3
  },
  {
    "outfit_name": "Total look",
    "price": 76.2,
    "brand": "H&M",
    "location": "H&M",
    "occasion": "Other",
    "colour": "Multi",
    "notes": "Good quality",
    "image": "https://res.cloudinary.com/dw8fpwkkn/image/upload/v1623430902/outfit28_eogzkn.jpg",
    "gender": "Women",
    "user_id": 3
  },
  {
    "outfit_name": "Total look",
    "price": 57.7,
    "brand": "H&M",
    "location": "H&M",
    "occasion": "Other",
    "colour": "Multi",
    "notes": "Good quality",
    "image": "https://res.cloudinary.com/dw8fpwkkn/image/upload/v1623430902/outfit28_eogzkn.jpg",
    "gender": "Women",
    "user_id": 3
  },
  {
    "outfit_name": "Summer look",
    "price": 87.7,
    "brand": "H&M",
    "location": "H&M",
    "occasion": "Other",
    "colour": "Multi",
    "notes": "Good quality",
    "image": "https://res.cloudinary.com/dw8fpwkkn/image/upload/v1623430901/outfit21_plotdu.jpg",
    "gender": "Women",
    "user_id": 3
  },
  {
    "outfit_name": "Picnic look",
    "price": 87.7,
    "brand": "H&M",
    "location": "H&M",
    "occasion": "Other",
    "colour": "Green",
    "notes": "Good quality",
    "image": "https://res.cloudinary.com/dw8fpwkkn/image/upload/v1623430902/outfit27_ngi5sp.jpg",
    "gender": "Women",
    "user_id": 3
  },
  {
    "outfit_name": "Dress",
    "price": 57.7,
    "brand": "H&M",
    "location": "H&M",
    "occasion": "Other",
    "colour": "Multi",
    "notes": "Good quality",
    "image": "https://res.cloudinary.com/dw8fpwkkn/image/upload/v1623430902/outfit26_tbkmor.jpg",
    "gender": "Women",
    "user_id": 3
  },
  {
    "outfit_name": "Suit",
    "price": 97.7,
    "brand": "H&M",
    "location": "H&M",
    "occasion": "Wedding",
    "colour": "Yellow",
    "notes": "Good quality",
    "image": "https://res.cloudinary.com/dw8fpwkkn/image/upload/v1623430900/outfit17_cft9ce.jpg",
    "gender": "Women",
    "user_id": 3
  },
  {
    "outfit_name": "Dress",
    "price": 97.7,
    "brand": "H&M",
    "location": "H&M",
    "occasion": "Wedding",
    "colour": "Blue",
    "notes": "Good quality",
    "image": "https://res.cloudinary.com/dw8fpwkkn/image/upload/v1623430901/outfit23_swa4n0.jpg",
    "gender": "Women",
    "user_id": 3
  },
  {
    "outfit_name": "Nice outfit",
    "price": 97.7,
    "brand": "H&M",
    "location": "H&M",
    "occasion": "Other",
    "colour": "Brown",
    "notes": "Good quality",
    "image": "https://res.cloudinary.com/dw8fpwkkn/image/upload/v1623430901/outfit22_onx6z9.jpg",
    "gender": "Women",
    "user_id": 3
  },
  {
    "outfit_name": "Cool outfit",
    "price": 57.7,
    "brand": "H&M",
    "location": "H&M",
    "occasion": "Other",
    "colour": "Pink",
    "notes": "Good quality",
    "image": "https://res.cloudinary.com/dw8fpwkkn/image/upload/v1623430901/outfit18_v5zung.jpg",
    "gender": "Men",
    "user_id": 3
  },
  {
    "outfit_name": "Cool outfit",
    "price": 57.7,
    "brand": "H&M",
    "location": "H&M",
    "occasion": "Other",
    "colour": "White",
    "notes": "Good quality",
    "image": "https://res.cloudinary.com/dw8fpwkkn/image/upload/v1623430902/outfit24_a1bggl.jpg",
    "gender": "Men",
    "user_id": 3
  },
  {
    "outfit_name": "Beach outfit",
    "price": 57.7,
    "brand": "H&M",
    "location": "H&M",
    "occasion": "Swimwear",
    "colour": "Multi",
    "notes": "Good quality",
    "image": "https://res.cloudinary.com/dw8fpwkkn/image/upload/v1623430900/outfit20_ynnz8a.jpg",
    "gender": "Women",
    "user_id": 3
  },
  {
    "outfit_name": "Nite outfit",
    "price": 57.7,
    "brand": "H&M",
    "location": "H&M",
    "occasion": "Other",
    "colour": "Multi",
    "notes": "Good quality",
    "image": "https://res.cloudinary.com/dw8fpwkkn/image/upload/v1623430900/outfit19_lwy9sc.jpg",
    "gender": "Women",
    "user_id": 3
  }
]
